mcautograder/__init__.py
mcautograder/notebook.py
mcautograder/utils.py
mcautograder-0.0.6.dist-info/LICENSE
mcautograder-0.0.6.dist-info/METADATA
mcautograder-0.0.6.dist-info/WHEEL
mcautograder-0.0.6.dist-info/top_level.txt
mcautograder-0.0.6.dist-info/RECORD
