Metadata-Version: 2.1
Name: mcautograder
Version: 0.0.6
Summary: Small multiple choice question autograding library
Home-page: https://github.com/chrispyles/mcautograder
Author: Chris Pyles
Author-email: cpyles@berkeley.edu
License: BSD-3-Clause
Platform: UNKNOWN
Classifier: Programming Language :: Python :: 3
Classifier: License :: OSI Approved :: BSD License
Classifier: Operating System :: OS Independent
